Metadata-Version: 1.0
Name: sujataBasicCal
Version: 0.1.0
Summary: A very basic calculator
Home-page: UNKNOWN
Author: Me
Author-email: UNKNOWN
License: MIT
Platform: UNKNOWN
